mongodbconnpackage/__init__.py
mongodbconnpackage/mongo_crud.py
mongodbconnpackage-0.0.0.dist-info/LICENSE
mongodbconnpackage-0.0.0.dist-info/METADATA
mongodbconnpackage-0.0.0.dist-info/WHEEL
mongodbconnpackage-0.0.0.dist-info/top_level.txt
mongodbconnpackage-0.0.0.dist-info/RECORD
